news_scrapper/__init__.py
news_scrapper/news_scrapper.py
news_scrapper-0.1.0.dist-info/METADATA
news_scrapper-0.1.0.dist-info/WHEEL
news_scrapper-0.1.0.dist-info/entry_points.txt
news_scrapper-0.1.0.dist-info/top_level.txt
news_scrapper-0.1.0.dist-info/RECORD
