Metadata-Version: 2.1
Name: news-scrapper
Version: 0.1.0
Summary: A web scraper for Investopedia news headlines
Home-page: https://github.com/Demon-2-Angel/Daily_Financial_News_Automation
Author: Aniruddha Kumar
Author-email: foraniruddhakumar@gmail.com
License: UNKNOWN
Platform: UNKNOWN
Classifier: Programming Language :: Python :: 3
Classifier: License :: OSI Approved :: MIT License
Classifier: Operating System :: OS Independent
Requires-Python: >=3.6
Requires-Dist: selenium
Requires-Dist: pandas
